{
    "uuid": "14e696ad-4fb9-4693-8fd1-a84cd2ce41ea",
    "name": "石首人民广播电台",
    "url": "http://sstvplay.ssgdlive.com/live/radio.m3u8",
    "homepage": "http://m.youabc.cn/keyword/k_889510.html",
    "favicon": "https://bkimg.cdn.bcebos.com/pic/060828381f30e924b899f320e44179061d950a7b59c2?x-bce-process=image/watermark,image_d2F0ZXIvYmFpa2U5Mg==,g_7,xp_5,yp_5/format,f_auto",
    "creation": "2021-03-08 22:19:20",
    "country": "China",
    "country_code": "CN",
    "language": "chinese",
    "tags": "news",
    "state": "Hupei",
    "bitrate": 0
}