{
    "uuid": "2028a03f-36ab-4db7-8d31-569533108216",
    "name": "B98.5 FM",
    "url": "https://playerservices.streamtheworld.com/api/livestream-redirect/KURBFMAAC.aac",
    "homepage": "https://www.b98.com",
    "favicon": "https://radiostationusa.fm/assets/image/radio/180/KURB.png",
    "creation": "2021-02-07 13:11:48",
    "country": "The United States Of America",
    "country_code": "US",
    "language": "english",
    "tags": "adult contemporary",
    "state": "Little Rock AR",
    "bitrate": 48
}