{
    "uuid": "21739268-31e3-499f-8ba2-03444154fca0",
    "name": "Ice Radio The Alternative",
    "url": "https://stream.iceradio.nl/iceradio",
    "homepage": "https://iceradio.nl",
    "favicon": "https://iceradio.nl/wp-content/uploads/2020/07/cropped-IceRadio-Pinguin-1-32x32.jpg",
    "creation": "2021-02-07 13:11:48",
    "country": "The Netherlands",
    "country_code": "NL",
    "language": "nederlands",
    "tags": "no playlist,no ads,reggae,blues,grunge,oldies,classic rock,jazz,non-commercial,rock,10s,00s,90s,80s,70s,60s,alternative,pop",
    "state": "Utrecht",
    "bitrate": 0
}