{
    "uuid": "2cad68d6-b18b-4a02-9e82-203e8cd5a413",
    "name": "Rádio RockBr",
    "url": "http://hts09.kshost.com.br:8190",
    "homepage": "https://radiorockbr.com.br/rockbrasil/",
    "favicon": "https://radiorockbr.com.br/rockbrasil/wp-content/uploads/2016/02/cropped-logo-radio-rockbr-200px.png",
    "creation": "2021-02-07 13:11:49",
    "country": "Brazil",
    "country_code": "BR",
    "language": "português do brasil",
    "tags": "a casa do rock nacional,rock brazuca,rock nacional",
    "state": "São Paulo",
    "bitrate": 64
}