{
    "uuid": "539656b1-d639-46c7-aa3e-b369e3bcdb99",
    "name": "都江堰人民广播电台",
    "url": "http://live.xmcdn.com/live/2360/64.m3u8",
    "homepage": "http://www.djy.gov.cn/dyjgb_rmzfwz/c129233/video_list.shtml",
    "favicon": "https://bkimg.cdn.bcebos.com/pic/d31b0ef41bd5ad6eddc450413d822edbb6fd5266964d?x-bce-process=image/watermark,image_d2F0ZXIvYmFpa2UyNzI=,g_7,xp_5,yp_5",
    "creation": "2021-02-07 13:11:49",
    "country": "China",
    "country_code": "CN",
    "language": "chinese",
    "tags": "music",
    "state": "Szechuan",
    "bitrate": 0
}