{
    "uuid": "706b72b4-792a-4be4-a4e6-c245aae5ffc2",
    "name": "Laut.fm/radioparty",
    "url": "http://stream.laut.fm/radioparty",
    "homepage": "https://radioparty.godaddysites.com/",
    "favicon": "https://img1.wsimg.com/isteam/ip/552c7ad0-3865-4439-b7e8-004a7dff0f00/lightning-2295075_1280%201%20745x720.jpg/:/cr=t:0%25,l:0%25,w:100%25,h:100%25/rs=w:700,cg:true",
    "creation": "2021-02-07 13:11:48",
    "country": "Germany",
    "country_code": "DE",
    "language": "deutsch",
    "tags": "laut.fm/radioparty info zur veranstaltung von unsere künstler und immer neue hits am start aus den aktuelle charts und news und nachrichten und das wetter info über unsere radiopartner auf unser radiowebseite ?,rund um die uhr für euch spielen wir für euch ein mix dance,rock,schlager,discofox oldies,techno,pop,trance,house,80's,90's,,top40 charts 2000er club musik party-hits hands up hardstyle und noch mehr. wir wünschen euch viel spaß 24/7 .",
    "state": "Deutschland und NRW",
    "bitrate": 128
}