{
    "uuid": "79137d7a-23b2-11e8-91bf-52543be04c81",
    "name": "Clásica 88.5 (HJSA, 88.5 MHz FM, Cali)",
    "url": "http://69.30.243.166:9434/listen.mp3?0.6178945254749736",
    "homepage": "http://www.clasica885.com/",
    "favicon": "http://www.clasica885.com/wp-content/uploads/2017/09/logo-clasica.png",
    "creation": "2021-02-07 13:11:47",
    "country": "Colombia",
    "country_code": "CO",
    "language": "spanish",
    "tags": "instrumental,easy listening,classical",
    "state": "Valle del Cauca",
    "bitrate": 128
}