{
    "uuid": "801f298a-1c47-4940-b232-a5aa0960cafb",
    "name": "La Comadre Hermosillo - 102.7 FM - XHDM-FM - Hermosillo, SO",
    "url": "https://playerservices.streamtheworld.com/api/livestream-redirect/XHDMAAC.aac",
    "homepage": "https://www.iheart.com/live/la-comadre-1027-8078/",
    "favicon": "https://i.iheart.com/v3/re/new_assets/8ed325bb-fbce-44bc-879e-ba53cf652e2c?ops=fit(240%2C240)",
    "creation": "2021-02-28 07:03:18",
    "country": "Mexico",
    "country_code": "MX",
    "language": "español",
    "tags": "musica regional,regional mexican,musica regional mexicana,banda,grupera,mx,mex,méxico,sonora,hermosillo,iheart radio,iheart,radio,estación,fm,102.7,102.7 fm,acir,grupo acir,puros éxitos!!!,la comadre",
    "state": "Sonora",
    "bitrate": 48
}