{
    "uuid": "8b526005-1989-4d9a-9d55-661f5e1b430e",
    "name": "Alkarma TV Australia",
    "url": "https://5b622f07944df.streamlock.net/alkarmatv.com/alkarmaau.smil/chunklist_w377932823_b1628000_slar.m3u8",
    "homepage": "https://en.alkarmatv.com/live/aus/",
    "favicon": "https://i1.wp.com/en.alkarmatv.com/wp-content/uploads/2020/02/Logo-AU.png?resize=150%2C150\u0026ssl=1",
    "creation": "2021-02-19 19:40:45",
    "country": "Australia",
    "country_code": "AU",
    "language": "",
    "tags": "tv,christian",
    "state": "",
    "bitrate": 0
}