{
    "uuid": "9606d759-0601-11e8-ae97-52543be04c81",
    "name": "WGTK \"The Answer\" 970 AM Louisville, KY",
    "url": "http://provisioning.streamtheworld.com/pls/WGTKAMAAC.pls",
    "homepage": "http://970amtheanswer.com/",
    "favicon": "http://media.salemwebnetwork.com/saleminteractivemedia/newstalk/res/image/WGTK/header_logo.png",
    "creation": "2021-02-07 13:11:47",
    "country": "The United States Of America",
    "country_code": "US",
    "language": "english",
    "tags": "conservative,talk,news,louisville",
    "state": "Kentucky",
    "bitrate": 32
}