{
    "uuid": "96095448-0601-11e8-ae97-52543be04c81",
    "name": "KABC 790 Los Angeles, CA",
    "url": "http://provisioning.streamtheworld.com/pls/KABCAMAAC.pls",
    "homepage": "http://www.kabc.com/",
    "favicon": "http://www.kabc.com/wp-content/uploads/sites/320/2016/08/KABC-2016-sitelogo3.png",
    "creation": "2021-02-07 13:11:46",
    "country": "The United States Of America",
    "country_code": "US",
    "language": "english",
    "tags": "los angeles,talk,news",
    "state": "California",
    "bitrate": 48
}