{
    "uuid": "960a6afd-0601-11e8-ae97-52543be04c81",
    "name": "KVOQ 102.3 -Colorado Public Radio \"OpenAir\" - Denver, CO  AAC",
    "url": "http://stream2.cprnetwork.org:8000/cpr3_aac",
    "homepage": "http://www.cpr.org",
    "favicon": "http://www.cpr.org/sites/default/files/styles/large/public/images/cpr-logo-square.png",
    "creation": "2021-02-07 13:11:46",
    "country": "The United States Of America",
    "country_code": "US",
    "language": "english",
    "tags": "denver,indie,adult album alternative,npr,public radio",
    "state": "Colorado",
    "bitrate": 48
}