{
    "uuid": "96141338-0601-11e8-ae97-52543be04c81",
    "name": "KTCU 88.7 \"The Choice\"  Fort Worth, TX",
    "url": "http://ktcustream01.is.tcu.edu:80/ktcu",
    "homepage": "https://ktcu.tcu.edu/",
    "favicon": "https://ktcu.tcu.edu/wp-content/themes/tcu_journalism/library/images/apple-icon-touch.png",
    "creation": "2021-02-07 13:11:46",
    "country": "The United States Of America",
    "country_code": "US",
    "language": "english",
    "tags": "variety,fort worth",
    "state": "Texas",
    "bitrate": 0
}