{
    "uuid": "961a70e9-0601-11e8-ae97-52543be04c81",
    "name": "Wack Radio 90.1 - San Fernando",
    "url": "http://ample-zeno-07.radiojar.com/231zgkfyrxmtv",
    "homepage": "http://www.wackradio901fm.com/",
    "favicon": "http://www.wackradio901fm.com/images/stories/logo_300.png",
    "creation": "2021-02-07 13:11:47",
    "country": "Trinidad And Tobago",
    "country_code": "TT",
    "language": "english",
    "tags": "kaiso,news,calypso,soca,music,caribbean",
    "state": "San Fernando",
    "bitrate": 0
}