{
    "uuid": "961a12f3-0601-11e8-ae97-52543be04c81",
    "name": "CJRU 1280 \"The Scope\" Ryerson University - Toronto, ON",
    "url": "http://ryerson.out.airtime.pro:8000/ryerson_a",
    "homepage": "http://www.thescopeatryerson.ca/",
    "favicon": "http://www.thescopeatryerson.ca/themes/publication_2/theme_1/assets/img/logo.svg",
    "creation": "2021-02-07 13:11:47",
    "country": "Canada",
    "country_code": "CA",
    "language": "english",
    "tags": "community radio,university radio,toronto",
    "state": "Ontario",
    "bitrate": 128
}