{
    "uuid": "9629d012-0601-11e8-ae97-52543be04c81",
    "name": "Kiss FM 87.6, 87.8 \u0026 88.0 Melbourne, VIC",
    "url": "http://cc.net2streams.com:8565/kissfm.mp3",
    "homepage": "https://kissfm.com.au",
    "favicon": "http://kissfm.com.au/wp-content/uploads/2016/05/kiss-logo-105px.png",
    "creation": "2021-02-07 13:11:46",
    "country": "Australia",
    "country_code": "AU",
    "language": "english",
    "tags": "melbourne,electronica,dance",
    "state": "Victoria",
    "bitrate": 0
}