{
    "uuid": "962bb67c-0601-11e8-ae97-52543be04c81",
    "name": "Tonic Fitness Radio Terni",
    "url": "http://radioserver-professional.it:8000/radio-011",
    "homepage": "http://tonicnet.it/i-nostri-club/terni/",
    "favicon": "http://tonicnet.it/tonicnew/wp-content/themes/tonicnew/img/logo-tonic.svg",
    "creation": "2021-02-07 13:11:46",
    "country": "Italy",
    "country_code": "IT",
    "language": "italian",
    "tags": "top 40,pop,electronica",
    "state": "Umbria",
    "bitrate": 128
}