{
    "uuid": "962d55c6-0601-11e8-ae97-52543be04c81",
    "name": "KSKS 93.7 \"Kiss Country\" Fresno, CA",
    "url": "http://provisioning.streamtheworld.com/pls/KSKSFMAAC.pls",
    "homepage": "http://www.ksks.com/",
    "favicon": "http://cumulus.pro.poolb.tritondigitalcms.com/ksks-fm/wp-content/uploads/sites/464/2015/04/ksks-logo1.png",
    "creation": "2021-02-07 13:11:47",
    "country": "The United States Of America",
    "country_code": "US",
    "language": "english",
    "tags": "country,fresno",
    "state": "California",
    "bitrate": 48
}