{
    "uuid": "9634a8ba-0601-11e8-ae97-52543be04c81",
    "name": "KNWC \"Life 96.5\" Sioux Falls, SD",
    "url": "http://nwmedia-knwcfm.streamguys1.com/knwc-fm",
    "homepage": "http://life965.com/#",
    "favicon": "http://life965.com/wp-content/themes/nwm/images/logo-header-life965.png",
    "creation": "2021-02-07 13:11:46",
    "country": "The United States Of America",
    "country_code": "US",
    "language": "english",
    "tags": "contemporary christian,sioux falls",
    "state": "South Dakota",
    "bitrate": 0
}