{
    "uuid": "963774f3-0601-11e8-ae97-52543be04c81",
    "name": "106.3 The Lounge - Port Douglas, QLD",
    "url": "http://www.fast-serv.com/live/stream.pls?host=ic2329.c564.fast-serv.com\u0026port=80\u0026path=/stream",
    "homepage": "http://www.1063thelounge.com/",
    "favicon": "http://www.1063thelounge.com/images/perfect4relaxing.jpg",
    "creation": "2021-02-07 13:11:47",
    "country": "Australia",
    "country_code": "AU",
    "language": "english",
    "tags": "relax,lounge,smooth jazz",
    "state": "Queensland",
    "bitrate": 0
}