{
    "uuid": "9649276d-0601-11e8-ae97-52543be04c81",
    "name": "KWML \"Kool Oldies 104.5 \u0026 570\" Las Cruces, NM",
    "url": "http://provisioning.streamtheworld.com/pls/KWMLAMAAC.pls",
    "homepage": "http://kool1045fm.com/",
    "favicon": "http://kool1045fm.com/wp-content/uploads/sites/194/180x115-kwml-fm.png",
    "creation": "2021-02-07 13:11:47",
    "country": "The United States Of America",
    "country_code": "US",
    "language": "english",
    "tags": "oldies,las cruces",
    "state": "New Mexico",
    "bitrate": 64
}