{
    "uuid": "986eb516-8eb4-412b-83dc-8cbf796dc4cb",
    "name": "MIX Puerto Vallarta - 92.7 FM - XHVAY-FM - Grupo ACIR - Puerto Vallarta, JC",
    "url": "https://playerservices.streamtheworld.com/api/livestream-redirect/XHVAYFMAAC.aac",
    "homepage": "https://www.iheart.com/live/mix-927-6575/",
    "favicon": "https://i.iheart.com/v3/re/new_assets/5e55c5f1f2e817641ab904b2?ops=fit(240%2C240)",
    "creation": "2021-02-28 05:41:54",
    "country": "Mexico",
    "country_code": "MX",
    "language": "español",
    "tags": "pop,2010s,2000s,90s,80s,80s,90s y más,estación,iheart radio,iheart,radio,acir,grupo acir,fm,92.7,92.7 fm,mix,mix fm",
    "state": "Jalisco",
    "bitrate": 48
}