{
    "uuid": "b18d3b7c-c596-4c8a-9f5a-8117031119c0",
    "name": "Latino Mix 105.7/100.7",
    "url": "https://live.wostreaming.net/direct/univision-kvvffmaac-imc2",
    "homepage": "https://www.univision.com/radio/san-francisco-kvvf-fm",
    "favicon": "https://radiostationusa.fm/assets/image/radio/180/KVVF.png",
    "creation": "2021-02-07 13:11:48",
    "country": "The United States Of America",
    "country_code": "US",
    "language": "english",
    "tags": "spanish",
    "state": "Santa Clara CA",
    "bitrate": 32
}