{
    "uuid": "b8c227a9-721d-11ea-b1cf-52543be04c81",
    "name": "2EAR FM",
    "url": "http://198.74.51.37:9986/index.html?sid=1",
    "homepage": "http://2earfm.weebly.com/",
    "favicon": "https://2earfm.weebly.com/uploads/3/7/7/5/3775871/2earfm-bumper-sticker-small_orig.jpg",
    "creation": "2021-02-07 13:11:48",
    "country": "Australia",
    "country_code": "AU",
    "language": "english",
    "tags": "community radio,eurobodalla,102.9,107.5,moruya",
    "state": "NSW",
    "bitrate": 96
}