{
    "uuid": "b8c40f59-b436-11e8-afe1-52543be04c81",
    "name": "80s80s Mid Quality",
    "url": "http://80s80s.hoerradar.de/80s80s-mweb-mp3-mq?sABC=5o8o3686%230%232000r3268p2816383571rn5877123r83%23enqvbqr\u0026amsparams=playerid:radiode;skey:1535850118",
    "homepage": "https://www.80s80s.de/",
    "favicon": "http://static.rad.io/images/broadcasts/8f/c0/35911/1/t300.png",
    "creation": "2021-02-07 13:11:47",
    "country": "Germany",
    "country_code": "DE",
    "language": "",
    "tags": "80s",
    "state": "",
    "bitrate": 128
}