{
    "uuid": "c5fd8ae6-463a-11e9-aa55-52543be04c81",
    "name": "egoSOUL",
    "url": "https://egofm-soul.cast.addradio.de/egofm/soul/mp3/high/stream.mp3?ar-distributor=f0a2",
    "homepage": "https://www.egofm.de/streams/egosoul",
    "favicon": "https://www.egofm.de/content/images/stream/egofmsoul/egofm-soul-og.png",
    "creation": "2021-02-07 13:11:47",
    "country": "Germany",
    "country_code": "DE",
    "language": "german",
    "tags": "soul",
    "state": "Bavaria",
    "bitrate": 128
}