{
    "uuid": "d077ae1e-60ef-422b-b9ac-159e56b319d4",
    "name": "Svensk Folkmusik - AkkA radio",
    "url": "http://mediaserv38.live-streams.nl:8107/stream",
    "homepage": "http://www.svenskfolkmusik.nu",
    "favicon": "https://www.radioguide.fm/uploads/images/radiostation/20181209%20-%2011-AkkA-radio-kleinst.jpg",
    "creation": "2021-02-07 13:11:48",
    "country": "Sweden",
    "country_code": "SE",
    "language": "schwedisch,svenska,swedish",
    "tags": "traditional,swedish,svensk,folk,folk music,svensk folkmusik,folkmusik",
    "state": "",
    "bitrate": 192
}