{
    "uuid": "d1b3fa1f-cd49-424c-8644-94541a967910",
    "name": "9X Tashan TV",
    "url": "http://d2q8p4pe5spbak.cloudfront.net/bpk-tv/9Xtashan/9Xtashan.isml/9Xtashan-audio_208482_und=208000-video=877600.m3u8",
    "homepage": "http://www.9xtashan.in/",
    "favicon": "http://nettvss.live/uploads/allimg/19/1-19111Q342450-L.jpg",
    "creation": "2021-02-07 13:11:48",
    "country": "India",
    "country_code": "IN",
    "language": "punjabi",
    "tags": "",
    "state": "Maharashtra",
    "bitrate": 0
}