{
    "uuid": "e76f7cbb-168a-11e8-ae97-52543be04c81",
    "name": "RTBF Classic 21 - Soul Power",
    "url": "https://radios.rtbf.be/wr-c21-soul-128.mp3",
    "homepage": "http://www.rtbfradioplayer.be/radio/liveradio/webradio-classic21-soul",
    "favicon": "http://marpimagecache.s3.amazonaws.com/image/26_300x170_2017-08-28-07-15-13-46.png",
    "creation": "2021-02-07 13:11:47",
    "country": "Belgium",
    "country_code": "BE",
    "language": "french",
    "tags": "rtbf,soul",
    "state": "",
    "bitrate": 192
}