{
    "uuid": "f708ca3a-111c-11ea-a87e-52543be04c81",
    "name": "1980s Radio",
    "url": "https://samcloud.spacial.com/api/listen?sid=111415\u0026rid=191984\u0026f=mp3,any\u0026br=64000,any\u0026m=pls",
    "homepage": "http://internetradio.fun",
    "favicon": "https://prosamcloudmedia.blob.core.windows.net/110682-public/b830cb6a-80b4-4d0f-b384-fb92b3b4aca7_144x144.jpg",
    "creation": "2021-02-07 13:11:48",
    "country": "The United States Of America",
    "country_code": "US",
    "language": "spanish,american,british,english",
    "tags": "eighties,non-commercial,pop rock,adult contemporary,classic hits,latino-pop,24/7,non-stop,decades,80,1980,1980s,80s",
    "state": "Michigan",
    "bitrate": 128
}