{
    "uuid": "04107817-118d-49ac-851b-0d81d4084a10",
    "name": "כאן קול המוסיקה - Kan Kol Hamusica",
    "url": "http://kanliveicy.media.kan.org.il/icy/kankolhamusica_mp3",
    "homepage": "https://www.kan.org.il/live/radio.aspx?stationid=7",
    "favicon": "https://kanweb.blob.core.windows.net/download/pictures/Logo_Color7_img_.png",
    "creation": "2021-02-07 13:11:48",
    "country": "Israel",
    "country_code": "IL",
    "language": "עברית,hebrew",
    "tags": "classical,ilstations",
    "state": "",
    "bitrate": 0
}