{
    "uuid": "187a3453-d587-4d69-a740-1c1a4cc055b0",
    "name": "ABC Radio Perth 720 (Public Radio)",
    "url": "http://www.abc.net.au/res/streaming/audio-live/shout-mp3/local_perth.pls",
    "homepage": "http://www.abc.net.au/res/streaming/audio-live/shout-mp3/local_perth.pls",
    "favicon": "",
    "creation": "2021-02-07 13:11:48",
    "country": "Australia",
    "country_code": "AU",
    "language": "english",
    "tags": "abc radio perth 720 (public radio)",
    "state": "Western Australia",
    "bitrate": 64
}