{
    "uuid": "19942853-8eb6-11ea-8564-52543be04c81",
    "name": "RadioKP",
    "url": "http://russia.radiokp128.mp3.streamr.ru",
    "homepage": "https://www.krsk.kp.ru/radio/26508/3377815/",
    "favicon": "https://scontent-arn2-1.xx.fbcdn.net/v/t1.0-9/p960x960/91007079_2988313357878525_893124911466283008_o.png?_nc_cat=103\u0026_nc_sid=85a577\u0026_nc_ohc=XLvo8MpIW10AX8qrK4r\u0026_nc_ht=scontent-arn2-1.xx\u0026oh=88c658994370c0a015b0f30d70cc3dea\u0026oe=5ED691FB",
    "creation": "2021-02-07 13:11:48",
    "country": "",
    "country_code": "",
    "language": "ru",
    "tags": "news,podcast",
    "state": "Moscow\n",
    "bitrate": 0
}