{
    "uuid": "1ea02dcd-207a-4973-974e-d40d4f2b5fde",
    "name": "黔南综合广播",
    "url": "https://lhttp.qingting.fm/live/5022717/64k.mp3",
    "homepage": "http://www.qnz.com.cn/",
    "favicon": "https://bkimg.cdn.bcebos.com/pic/1ad5ad6eddc451da81cbcede7eb44566d016092494e6?x-bce-process=image/watermark,image_d2F0ZXIvYmFpa2U5Mg==,g_7,xp_5,yp_5",
    "creation": "2021-02-07 13:11:49",
    "country": "China",
    "country_code": "CN",
    "language": "chinese",
    "tags": "news",
    "state": "Kweichow",
    "bitrate": 0
}