{
    "uuid": "22cb8a0b-ac40-479d-a823-fabc83961618",
    "name": "99.9 Gator Country",
    "url": "https://playerservices.streamtheworld.com/api/livestream-redirect/WGNEAAC.aac",
    "homepage": "https://www.999gatorcountry.com",
    "favicon": "https://radiostationusa.fm/assets/image/radio/180/WGNE-FM.png",
    "creation": "2021-02-07 13:11:48",
    "country": "The United States Of America",
    "country_code": "US",
    "language": "english",
    "tags": "country",
    "state": "Middleburg FL",
    "bitrate": 64
}