{
    "uuid": "29a7bd6b-aec8-4bca-8006-2e0f5f95371f",
    "name": "徐州农村广播",
    "url": "https://lhttp.qingting.fm/live/20211623/64k.mp3",
    "homepage": "http://www.xzgd.com/login/Login.jsp?logintype=1",
    "favicon": "https://bkimg.cdn.bcebos.com/pic/80cb39dbb6fd526643dd334ca418972bd50736f7?x-bce-process=image/watermark,image_d2F0ZXIvYmFpa2U4MA==,g_7,xp_5,yp_5",
    "creation": "2021-02-07 13:11:49",
    "country": "China",
    "country_code": "CN",
    "language": "chinese",
    "tags": "music",
    "state": "Kiangsu",
    "bitrate": 0
}