{
    "uuid": "421a40d5-ed29-4a1f-baaf-66eb933287f9",
    "name": "三门峡交通文艺广播",
    "url": "http://live.xmcdn.com/live/2706/64.m3u8",
    "homepage": "http://www.smxtv.net/",
    "favicon": "https://imagev2.xmcdn.com/group81/M08/0B/66/wKgPDV60umni7_spAABw1uDkA-I008.jpg!strip=1\u0026quality=7\u0026magick=webp\u0026op_type=5\u0026upload_type=cover\u0026name=web_large\u0026device_type=ios",
    "creation": "2021-02-07 13:11:49",
    "country": "China",
    "country_code": "CN",
    "language": "chinese",
    "tags": "golden oldies,music",
    "state": "Honan",
    "bitrate": 0
}