{
    "uuid": "43995901-3cda-11ea-8dd7-52543be04c81",
    "name": "Party Vibe Radio - Ambient",
    "url": "http://www.partyviberadio.com:8056/;stream/1",
    "homepage": "http://www.partyvibe.com",
    "favicon": "https://cdn-pv.azureedge.net/wp-content/uploads/2016/02/cropped-radio-tower-512-icon-2013105433-300x300.png",
    "creation": "2021-02-07 13:11:48",
    "country": "",
    "country_code": "",
    "language": "",
    "tags": "seashellradio,thimbleradio,relaxing,chillout,deep ambient,ambient,partyviberadio,non-commercial,commercial-free",
    "state": "",
    "bitrate": 320
}