{
    "uuid": "5b923707-d65f-4df8-bb93-97476c5801e6",
    "name": "Mothers Day Radio",
    "url": "https://stream.zeno.fm/48gxpvvnsp8uv",
    "homepage": "https://node-08.zeno.fm/48gxpvvnsp8uv?rj-ttl=5\u0026rj-tok=AAABeAfeCgQAcE6KikBfb2hvhw",
    "favicon": "https://ws.shoutcast.com/images/contacts/d/dec8/dec80395-6c98-4a1e-bc7b-069a1825f039/radios/a7f76d0d-b1a7-4a9f-b57e-c33f8e9e686b/a7f76d0d-b1a7-4a9f-b57e-c33f8e9e686b.png",
    "creation": "2021-03-06 14:06:13",
    "country": "The United Kingdom Of Great Britain And Northern Ireland",
    "country_code": "GB",
    "language": "english",
    "tags": "southampton,london,la comadre,dia de la madre,new music,top 40,oldies,vintage,hits,classical,rock,pop,why not make every day - a mothers day?,christian commentary/messages,dedications,interviews,live,00s,60s,70s,90s,80s,public radio,mothering sunday,mummy,mumbai,holiday,mothers,mothers day",
    "state": "",
    "bitrate": 0
}