{
    "uuid": "6e433bac-f036-11e8-a471-52543be04c81",
    "name": "Liquid Web Radio",
    "url": "http://ice.streamcloud.mediacdn.com/freeradio-1000",
    "homepage": "http://liquidfm.gr/",
    "favicon": "http://liquidfm.gr/templates/liquidfm_160810_161/images/designer/xacaf84c411463bed7140a541c31e7288_liquidlogo.png.pagespeed.ic.928Rkzl2o2.png",
    "creation": "2021-02-07 13:11:47",
    "country": "Greece",
    "country_code": "GR",
    "language": "",
    "tags": "electronic",
    "state": "",
    "bitrate": 256
}