{
    "uuid": "87185d9b-6f99-4cd0-8077-8b67ce906e9f",
    "name": "95.9 The Rat",
    "url": "https://playerservices.streamtheworld.com/api/livestream-redirect/WRATFMAAC.aac",
    "homepage": "https://wrat.com",
    "favicon": "https://radiostationusa.fm/assets/image/radio/180/WRATFM.png",
    "creation": "2021-02-07 13:11:48",
    "country": "The United States Of America",
    "country_code": "US",
    "language": "english",
    "tags": "rock",
    "state": "Point Pleasant NJ",
    "bitrate": 64
}