{
    "uuid": "9608d172-0601-11e8-ae97-52543be04c81",
    "name": "Antenna Radio Esse",
    "url": "http://s8.mediastreaming.it:9058/;stream.mp3",
    "homepage": "http://www.antennaradioesse.it/",
    "favicon": "https://scontent-mxp1-1.xx.fbcdn.net/v/t1.0-1/p200x200/15826912_1201578936556444_1486858673664911136_n.png?oh=72a646c388a6fa3ff8cf914c78094fd6\u0026oe=5A11E167",
    "creation": "2021-02-07 13:11:46",
    "country": "Italy",
    "country_code": "IT",
    "language": "italian",
    "tags": "siena,local programming",
    "state": "Toscana",
    "bitrate": 128
}