{
    "uuid": "961b93a7-0601-11e8-ae97-52543be04c81",
    "name": "Antenne Niedersachsen Deutsch",
    "url": "http://stream.antenne.com/deutsch/mp3-192/linux/",
    "homepage": "http://webradio.antenne.com/",
    "favicon": "http://webradio.antenne.com/apple-touch-icon.png",
    "creation": "2021-02-07 13:11:47",
    "country": "Germany",
    "country_code": "DE",
    "language": "german",
    "tags": "00s,90s,80s,oldies,new age,deutsche lieder,deutschrock",
    "state": "Lower Saxony",
    "bitrate": 0
}