{
    "uuid": "961d5912-0601-11e8-ae97-52543be04c81",
    "name": "WXNA 101.5 Nashville, TN \"Low Power, High Voltage\"",
    "url": "http://listen.wxnafm.org:8000/stream",
    "homepage": "http://www.wxnafm.org/",
    "favicon": "http://static1.squarespace.com/static/549081cfe4b0d5014e3470e3/t/56fd75f12fe131ccf8df7870/1475689140193/?format=1000w",
    "creation": "2021-02-07 13:11:46",
    "country": "The United States Of America",
    "country_code": "US",
    "language": "",
    "tags": "nashville,freeform,community radio",
    "state": "Tennessee",
    "bitrate": 128
}