{
    "uuid": "961e050e-0601-11e8-ae97-52543be04c81",
    "name": "Radio Arabella Classic Rock",
    "url": "http://rs32.stream24.net/arabella-rock.mp3",
    "homepage": "http://radioarabellaclassicrock.radio.de/",
    "favicon": "https://scontent.ftxl1-1.fna.fbcdn.net/v/t1.0-9/fr/cp0/e15/q65/549742_491787817514532_757596421_n.jpg?oh=f8c4cdad2ba2f2f3591355cf485c4bc4\u0026oe=59E134F4",
    "creation": "2021-02-07 13:11:47",
    "country": "Germany",
    "country_code": "DE",
    "language": "german",
    "tags": "music,hits,rock,soft rock,classic rock",
    "state": "München",
    "bitrate": 128
}