{
    "uuid": "9620b4f7-0601-11e8-ae97-52543be04c81",
    "name": "CFAX 1070 (Victoria, BC)",
    "url": "http://provisioning.streamtheworld.com/pls/CFAXAMAAC.pls",
    "homepage": "http://www.iheartradio.ca/cfax-1070",
    "favicon": "https://i2.wp.com/www.camcd-acdcm.ca/wp-content/uploads/2016/11/CFAX_logo.jpg?resize=450%2C450\u0026ssl=1",
    "creation": "2021-02-07 13:11:47",
    "country": "Canada",
    "country_code": "CA",
    "language": "english",
    "tags": "talk,local news,news,commercial,news talk",
    "state": "British Columbia",
    "bitrate": 40
}