{
    "uuid": "96269e0a-0601-11e8-ae97-52543be04c81",
    "name": "KUAF-HD3 Jazz Stream - Fayetteville, AR",
    "url": "https://war.streamguys1.com:7031/kuaf3",
    "homepage": "http://kuaf.com/",
    "favicon": "http://mediad.publicbroadcasting.net/p/kuaf/files/201508/favicon_fid.ico",
    "creation": "2021-02-07 13:11:46",
    "country": "The United States Of America",
    "country_code": "US",
    "language": "english",
    "tags": "fayetteville,jazz,public radio",
    "state": "Arkansas",
    "bitrate": 96
}