{
    "uuid": "96273f91-0601-11e8-ae97-52543be04c81",
    "name": "KLSU 91.1 Louisiana State University - Baton Rouge, LA",
    "url": "http://130.39.238.143:8010/stream.aac",
    "homepage": "http://www.lsunow.com/klsu/",
    "favicon": "http://bloximages.newyork1.vip.townnews.com/lsunow.com/content/tncms/custom/image/df0ae1da-be4a-11e5-81e6-2b7c24bef43a.png?_dc=1453166450",
    "creation": "2021-02-07 13:11:46",
    "country": "The United States Of America",
    "country_code": "US",
    "language": "english",
    "tags": "college radio,baton rouge",
    "state": "Louisiana",
    "bitrate": 0
}