{
    "uuid": "9629ca98-0601-11e8-ae97-52543be04c81",
    "name": "WKCR 89.9 Columbia University - New York, NY",
    "url": "http://wkcr.streamguys1.com:80/live",
    "homepage": "https://www.cc-seas.columbia.edu/wkcr/",
    "favicon": "http://static.radio.net/images/broadcasts/8b/e9/14215/c175.png",
    "creation": "2021-02-07 13:11:47",
    "country": "The United States Of America",
    "country_code": "US",
    "language": "english",
    "tags": "new york city,spoken art,art music,alternative,jazz",
    "state": "New York",
    "bitrate": 0
}