{
    "uuid": "963f632e-0601-11e8-ae97-52543be04c81",
    "name": "WKPW 90.7 \"Classic Hits\" Knightstown, IN",
    "url": "http://165.139.147.234:8081/wkpw",
    "homepage": "http://www.wkpwfm.com/",
    "favicon": "http://web03.cabeard.k12.in.us/wkpw/Classic%20Hits%20Blue%20Swirl%20512%20x%20512%20px%20red%20\u0026%20yellow.jpg",
    "creation": "2021-02-07 13:11:47",
    "country": "The United States Of America",
    "country_code": "US",
    "language": "english",
    "tags": "knightstown,classic hits,classic rock,oldies",
    "state": "Indiana",
    "bitrate": 128
}