{
    "uuid": "9643f7d1-0601-11e8-ae97-52543be04c81",
    "name": "WEGE 104.9 \"The Eagle\" Lima, OH",
    "url": "http://crystalout.surfernetwork.com:8001/WEGE-FM_MP3",
    "homepage": "http://1049theeagle.com/",
    "favicon": "http://1049theeagle.com//wp-content/uploads/2016/08/favicon.ico",
    "creation": "2021-02-07 13:11:47",
    "country": "The United States Of America",
    "country_code": "US",
    "language": "english",
    "tags": "lima,classic rock",
    "state": "Ohio",
    "bitrate": 0
}