{
    "uuid": "9646d408-0601-11e8-ae97-52543be04c81",
    "name": "WHTF \"Hot 104.9\" Havana, FL",
    "url": "http://provisioning.streamtheworld.com/pls/WHTFAAC.pls",
    "homepage": "http://www.hot1049.com/",
    "favicon": "http://www.hot1049.com/wp-content/uploads/sites/5/2017/01/HOT1049-Logo_Vertical-with-tag_web_small-e1484317267197.jpg",
    "creation": "2021-02-07 13:11:47",
    "country": "The United States Of America",
    "country_code": "US",
    "language": "english",
    "tags": "havana,tallahassee,contemporary hits,top 40",
    "state": "Florida",
    "bitrate": 64
}