{
    "uuid": "964ae5e0-0601-11e8-ae97-52543be04c81",
    "name": "KLUR 99.9 Wichita Falls, TX",
    "url": "http://provisioning.streamtheworld.com/pls/KLURFMAAC.pls",
    "homepage": "http://www.klur.com/",
    "favicon": "http://cumulus.pro.poolb.tritondigitalcms.com/klur-fm/wp-content/uploads/sites/338/2015/03/site-logo.png",
    "creation": "2021-02-07 13:11:47",
    "country": "The United States Of America",
    "country_code": "US",
    "language": "english",
    "tags": "country,wichita falls",
    "state": "Texas",
    "bitrate": 48
}