{
    "uuid": "9e36742e-69ad-491d-9d05-2845b7022a6c",
    "name": "Tropicalisima 1350 AM \"El sonido de la calle\" (XEQK) IMER",
    "url": "https://s2.mexside.net/8030/stream",
    "homepage": "https://www.imer.mx/tropicalisima/",
    "favicon": "https://www.imer.mx/wp-content/uploads/sites/36/cvr_tropicalisima_2018.jpg",
    "creation": "2021-02-07 13:11:48",
    "country": "Mexico",
    "country_code": "MX",
    "language": "español,español latino,spanish",
    "tags": "musica tropical,salsa,cumbia,merengue,bachata,danzon,chachacha,mambo,bolero,musica latinoamericana,musica mexicana,hora exacta,estado de mexico,ciudad de mexico,mexico city,mexico",
    "state": "Ciudad de México",
    "bitrate": 96
}