{
    "uuid": "9f9651ee-6825-43d1-950b-b1f9c7ff1c2c",
    "name": "Radioachterhoek.nl",
    "url": "https://stream.radioachterhoek.nl/index.html?sid=1",
    "homepage": "https://radioachterhoek.nl",
    "favicon": "https://radioachterhoek.nl/cropped-fb-cover-01-png",
    "creation": "2021-02-07 13:11:49",
    "country": "The Netherlands",
    "country_code": "NL",
    "language": "dutch/english",
    "tags": "80s,70s,60s,50s,public radio,radioachterhoek,achterhoek",
    "state": "",
    "bitrate": 320
}