{
    "uuid": "c1bdcc29-4d8e-45f1-9069-8b7882a233bb",
    "name": "_Radio Energy(Argentina)",
    "url": "https://gmusto.radioca.st/mp3",
    "homepage": "https://www.radioenergy.to",
    "favicon": "https://www.radioenergy.org/LogoEnergy.png",
    "creation": "2021-02-07 13:11:49",
    "country": "Argentina",
    "country_code": "AR",
    "language": "italiano",
    "tags": "pop,top 100,top40,top40,hits,adult hits,adult contemporary,classic italian pop,classic italian pop,italian pop,italian pop,classic pop,classic hits,evergreen,evergreens,oldies,2000s,90s,80s,70s",
    "state": "Buenos Aires",
    "bitrate": 192
}