{
    "uuid": "f2a3997b-8901-455f-b003-dce8fba62ab6",
    "name": "Nordpolradio",
    "url": "https://stream.laut.fm/nordpolradio",
    "homepage": "https://www.nordpolradio.de",
    "favicon": "https://www.nordpolradio.de/favicon.ico",
    "creation": "2021-02-07 13:11:48",
    "country": "Germany",
    "country_code": "DE",
    "language": "german",
    "tags": "natal,navidad,holiday,weihnachten,klassik weihnachten christmas,christmas music,christmas,xmas",
    "state": "North Rhine-Westphalia",
    "bitrate": 128
}