{
    "uuid": "f2ad7159-b75e-4da9-b376-68060773a36a",
    "name": "XEVA - 91.7 FM - XHVA-FM - Grupo Pazos - Villahermosa, TB",
    "url": "http://signals.centrocibernetico.com:29030/;",
    "homepage": "http://xeva.com.mx/",
    "favicon": "https://scontent.fvsa2-1.fna.fbcdn.net/v/t1.0-9/90348546_2837024759720924_8967024104884404224_o.png?_nc_cat=111\u0026ccb=3\u0026_nc_sid=09cbfe\u0026_nc_ohc=_8_mTKyipDcAX9bsbU4\u0026_nc_ht=scontent.fvsa2-1.fna\u0026oh=d89d88824548a8242826b7b19b95086a\u0026oe=605F8260",
    "creation": "2021-02-27 23:17:34",
    "country": "Mexico",
    "country_code": "MX",
    "language": "español,spanish",
    "tags": "la emisora del hogar,noticieros,noticias,música,xeva noticias,xhva,xhva-fm,sureste,radio núcleo comunicación oro,grupo pazos,mx,mex,tab,vhsa,villa,méxico,tabasco,villahermosa,radio hogar,radio,fm,91.7,91.7 fm,xeva",
    "state": "Tabasco",
    "bitrate": 48
}