{
    "uuid": "fb5ba72a-082b-4627-a444-22eb784032e3",
    "name": "Marrakech Plus",
    "url": "http://titan.shoutca.st:8264/",
    "homepage": "http://www.radioplusmarrakech.jimdo.com/",
    "favicon": "http://www.maghreb-radio.com/sites/default/files/styles/radio_medium_90x90/public/radio/radio-plus-marrakech_1.jpg?itok=QdItbYq3",
    "creation": "2021-02-07 13:11:48",
    "country": "Morocco",
    "country_code": "MA",
    "language": "français,arabic",
    "tags": "",
    "state": "",
    "bitrate": 128
}