{
    "uuid": "fdff7305-a92d-4a13-8d8a-069757db7854",
    "name": "Getsemani FM Semarang",
    "url": "https://freeuk13.listen2myradio.com/live.mp3?typeportmount=s1_8656_stream_25769714",
    "homepage": "https://aksesglobalmultimedia.com/radio/getsemani.html",
    "favicon": "https://aksesglobalmultimedia.com/radio/upload/getsemani.png",
    "creation": "2021-02-24 04:42:16",
    "country": "Indonesia",
    "country_code": "ID",
    "language": "english,indonesian",
    "tags": "media kristen,akses global multimedia,pop,rohani",
    "state": "Semarang",
    "bitrate": 0
}