{
    "uuid": "fe3e7c6e-1baa-11e8-a334-52543be04c81",
    "name": "R.SA Snow Fun",
    "url": "http://streams.rsa-sachsen.de/100/mp3-192/streams.rsa-sachsen.de/",
    "homepage": "http://rsa-sachsen.de/",
    "favicon": "http://media.streamabc.com/livestream.rsa-sachsen.de/100/RSA_SnowFun_600x600px_farbig.png",
    "creation": "2021-02-07 13:11:47",
    "country": "Germany",
    "country_code": "DE",
    "language": "german",
    "tags": "party,hits,schlager,10s,00s,90s,80s,70s,60s,50s,dance,disco,rnb,rock,pop,pop rock,oldies,contemporary",
    "state": "Saxony",
    "bitrate": 192
}